<annotation>
	<folder>3cea397d5b31edd853c2112724598081</folder>
	<filename>styrofoamSTYROFOAM (356).jpeg</filename>
	<path>3cea397d5b31edd853c2112724598081/styrofoamSTYROFOAM (356).jpeg</path>
	<source>
		<database>datature.io</database>
	</source>
	<size>
		<width>500</width>
		<height>500</height>
		<depth>3</depth>
	</size>
	<segmented>0</segmented>
	<object>
		<name>styrofoam</name>
		<pose>Unspecified</pose>
		<truncated>0</truncated>
		<difficult>0</difficult>
		<bndbox>
			<xmin>11.0</xmin>
			<ymin>67.0</ymin>
			<xmax>258.0</xmax>
			<ymax>278.0</ymax>
		</bndbox>
	</object>
</annotation>